bin/pygwalker_command.py
pygwalker/__init__.py
pygwalker/_constants.py
pygwalker/_typing.py
pygwalker/errors.py
pygwalker/api/__init__.py
pygwalker/api/adapter.py
pygwalker/api/anywidget.py
pygwalker/api/component.py
pygwalker/api/gradio.py
pygwalker/api/html.py
pygwalker/api/jupyter.py
pygwalker/api/kanaries_cloud.py
pygwalker/api/marimo.py
pygwalker/api/pygwalker.py
pygwalker/api/reflex.py
pygwalker/api/streamlit.py
pygwalker/api/webserver.py
pygwalker/communications/__init__.py
pygwalker/communications/anywidget_comm.py
pygwalker/communications/base.py
pygwalker/communications/gradio_comm.py
pygwalker/communications/hacker_comm.py
pygwalker/communications/reflex_comm.py
pygwalker/communications/streamlit_comm.py
pygwalker/data_parsers/__init__.py
pygwalker/data_parsers/base.py
pygwalker/data_parsers/cloud_dataset_parser.py
pygwalker/data_parsers/database_parser.py
pygwalker/data_parsers/modin_parser.py
pygwalker/data_parsers/pandas_parser.py
pygwalker/data_parsers/polars_parser.py
pygwalker/data_parsers/spark_parser.py
pygwalker/services/__init__.py
pygwalker/services/check_update.py
pygwalker/services/cloud_service.py
pygwalker/services/config.py
pygwalker/services/data_parsers.py
pygwalker/services/fname_encodings.py
pygwalker/services/format_invoke_walk_code.py
pygwalker/services/global_var.py
pygwalker/services/kaggle.py
pygwalker/services/kanaries_cli_login.py
pygwalker/services/preview_image.py
pygwalker/services/render.py
pygwalker/services/spec.py
pygwalker/services/streamlit_components.py
pygwalker/services/tip_tools.py
pygwalker/services/track.py
pygwalker/services/upload_data.py
pygwalker/templates/.gitignore
pygwalker/templates/index.html
pygwalker/templates/jupyter_iframe_message.html
pygwalker/templates/pygwalker_iframe.html
pygwalker/templates/pygwalker_main_page.html
pygwalker/templates/dist/dsl-to-workflow.umd.js
pygwalker/templates/dist/index.d.ts
pygwalker/templates/dist/pygwalker-app.es.js
pygwalker/templates/dist/pygwalker-app.iife.js
pygwalker-0.5.0.0.dist-info/METADATA
pygwalker-0.5.0.0.dist-info/WHEEL
pygwalker-0.5.0.0.dist-info/entry_points.txt
pygwalker-0.5.0.0.dist-info/licenses/LICENSE
pygwalker-0.5.0.0.dist-info/RECORD
