Metadata-Version: 2.4
Name: pygwalker
Version: 0.5.0.0
Summary: pygwalker: turn your data into an interactive UI for data exploration and visualization
Project-URL: homepage, https://kanaries.net/pygwalker
Project-URL: repository, https://github.com/Kanaries/pygwalker
Author-email: kanaries <support@kanaries.net>
License-File: LICENSE
Keywords: data-analysis,data-exploration,dataframe,jupyter,pandas,tableau,tableau-alternative,visualization
Classifier: License :: OSI Approved :: Apache Software License
Classifier: Programming Language :: Python :: 3
Requires-Python: >=3.7
Requires-Dist: anywidget
Requires-Dist: appdirs
Requires-Dist: arrow
Requires-Dist: astor
Requires-Dist: cachetools
Requires-Dist: duckdb<2.0.0,>=0.10.4
Requires-Dist: gw-dsl-parser==0.1.49.1
Requires-Dist: ipylab<=1.0.0
Requires-Dist: ipython
Requires-Dist: ipywidgets
Requires-Dist: jinja2
Requires-Dist: kanaries-track==0.0.5
Requires-Dist: numpy
Requires-Dist: packaging
Requires-Dist: pandas
Requires-Dist: psutil
Requires-Dist: pyarrow
Requires-Dist: pydantic
Requires-Dist: pytz
Requires-Dist: quickjs
Requires-Dist: requests
Requires-Dist: segment-analytics-python==2.2.3
Requires-Dist: sqlalchemy
Requires-Dist: sqlglot>=23.15.8
Requires-Dist: traitlets
Requires-Dist: typing-extensions
Provides-Extra: all
Requires-Dist: pandas; extra == 'all'
Requires-Dist: polars; extra == 'all'
Requires-Dist: reflex; extra == 'all'
Requires-Dist: streamlit; extra == 'all'
Provides-Extra: dev
Requires-Dist: build; extra == 'dev'
Requires-Dist: jupyter-server-proxy; extra == 'dev'
Requires-Dist: jupyterlab; extra == 'dev'
Requires-Dist: twine; extra == 'dev'
Provides-Extra: labv4
Requires-Dist: ipywidgets>=8.0.0; extra == 'labv4'
Requires-Dist: jupyter-client>7.4.9; extra == 'labv4'
Requires-Dist: jupyter-server>2.5.0; extra == 'labv4'
Provides-Extra: notebook
Requires-Dist: ipywidgets<8.0.0,>7.0.0; extra == 'notebook'
Requires-Dist: jupyter-client<=7.4.9,>6.0.0; extra == 'notebook'
Requires-Dist: jupyter-server<=2.5.0; extra == 'notebook'
Provides-Extra: pandas
Requires-Dist: pandas; extra == 'pandas'
Provides-Extra: polars
Requires-Dist: polars; extra == 'polars'
Provides-Extra: reflex
Requires-Dist: reflex; extra == 'reflex'
Provides-Extra: snowflake
Requires-Dist: pandas; extra == 'snowflake'
Requires-Dist: pyarrow==10.0.1; extra == 'snowflake'
Requires-Dist: snowflake-sqlalchemy==1.5.0; extra == 'snowflake'
Requires-Dist: sqlalchemy==1.4.49; extra == 'snowflake'
Provides-Extra: streamlit
Requires-Dist: streamlit; extra == 'streamlit'
